{
    "publication": "ZEINALI, H.; LEE, K.; ALAM, J.; BURGET, L. Text-dependent Speaker Verification Challenge 2024: Exploring Shared and User-defined Passphrases. In 2025 IEEE INTERNATIONAL CONFERENCE ON ACOUSTICS, SPEECH AND SIGNAL PROCESSING (ICASSP). Proceedings of the ... IEEE International Conference on Acoustics, Speech, and Signal Processing. Hyderabad, Indicka republika: Institute of Electrical and Electronics Engineers Inc., 2025. p. 1-5. Detail ZHANG, R.; WEI, J.; LU, X.; ZHANG, L.; JIN, D.; LU, W.; XU, J. Multi-Sinkhorn Teacher Knowledge Aggregation Framework for Adaptive Audio Anti-Spoofing. IEEE Transactions on Audio, Speech, and Language Processing, 2025, no. 33, p. 3850-3865. Detail ZHANG, R.; WEI, J.; LU, X.; ZHANG, L.; JIN, D.; XU, J.; LU, W. SHDA: Sinkhorn Domain Attention for Cross-Domain Audio Anti-Spoofing. IEEE Transactions on Information Forensics and Security, 2025, no. 20, p. 6474-6489. Detail ZHANG, Y.; TIAN, B.; ZHANG, L.; DUAN, Z. PartialEdit: Identifying Partial Deepfakes in the Era of Neural Speech Editing. In Proceedings of the Annual Conference of the International Speech Communication Association, INTERSPEECH. Interspeech. Rotterdam, Nizozemi: ISCA, 2025. p. 5353-5357.",
    "year": "2025",
    "title": "Text-dependent Speaker Verification Challenge 2024: Exploring Shared and User-defined Passphrases",
    "sections": {
        "type": {
            "label": "Type",
            "text": "conference paper"
        },
        "language": {
            "label": "Language",
            "text": "English"
        },
        "authors": {
            "label": "Authors",
            "text": "Zeinali Hossein Lee Kong Aik Alam Jahangir Burget Lukas, doc. Ing., Ph.D. , DCGM (FIT)"
        },
        "abstract": {
            "label": "Abstract",
            "text": "In contrast to text-independent speaker verification, which has received significant attention from researchers and has many competitions dedicated to it, text-dependent speaker verification (TdSV) has been less explored recently. The TdSV Challenge 2024 was organized to analyze and explore novel methods for this type of speaker verification and aims to motivate participants to develop new approaches to TdSV, conduct comprehensive analyses, and investigate advanced techniques such as self-supervised learning. This challenge builds on the achievements of the short-duration speaker verification (SdSV) Challenges held in 2020 and 2021 and focuses specifically on TdSV in two distinct scenarios. The first scenario involves conventional TdSV, while the second focuses on speaker enrollment using user-defined passphrases. This paper provides a detailed description of both tasks, introduces the evaluation rules, and presents a comprehensive analysis of the results obtained from this challenge."
        },
        "keywords": {
            "label": "Keywords",
            "text": "DeepMine dataset | TdSV Challenge | Text-dependent Speaker Verification | User-defined passphrase"
        },
        "published": {
            "label": "Published",
            "text": "2025"
        },
        "pages": {
            "label": "Pages",
            "text": "5"
        },
        "journal": {
            "label": "Journal",
            "text": "Proceedings of the ... IEEE International Conference on Acoustics, Speech, and Signal Processing, ISSN"
        },
        "proceedings": {
            "label": "Proceedings",
            "text": "2025 IEEE INTERNATIONAL CONFERENCE ON ACOUSTICS, SPEECH AND SIGNAL PROCESSING (ICASSP)"
        },
        "conference": {
            "label": "Conference",
            "text": "ICASSP 2025 - 2025 IEEE International Conference on Acoustics, Speech and Signal Processing (ICASSP)"
        },
        "publisher": {
            "label": "Publisher",
            "text": "Institute of Electrical and Electronics Engineers Inc."
        },
        "place": {
            "label": "Place",
            "text": "Hyderabad, Indicka republika"
        },
        "doi": {
            "label": "DOI",
            "text": "10.1109/ICASSP49660.2025.10888478"
        },
        "ut_wos": {
            "label": "UT WoS",
            "text": "001611514300080"
        },
        "eid_scopus": {
            "label": "EID Scopus",
            "text": "2-s2.0-105003888907"
        },
        "bibtex": {
            "label": "BibTeX",
            "text": "@inproceedings{BUT201393, author=\"{} and {} and {} and Lukas {Burget}\", title=\"Text-dependent Speaker Verification Challenge 2024: Exploring Shared and User-defined Passphrases\", booktitle=\"2025 IEEE INTERNATIONAL CONFERENCE ON ACOUSTICS, SPEECH AND SIGNAL PROCESSING (ICASSP)\", year=\"2025\", journal=\"Proceedings of the ... IEEE International Conference on Acoustics, Speech, and Signal Processing\", pages=\"5\", publisher=\"Institute of Electrical and Electronics Engineers Inc.\", address=\"Hyderabad, Indicka republika\", doi=\"10.1109/ICASSP49660.2025.10888478\", issn=\"1520-6149\", url=\"https://ieeexplore.ieee.org/stamp/stamp.jsp?tp=&arnumber=10888478\" }"
        },
        "files": {
            "label": "Files",
            "text": "- pdf zeinali_icassp2025_Text-dependent_Speaker_Verification_Challenge_2024_Exploring_Shared_and_User-defined_Passphrases.pdf 706 kB"
        },
        "projects": {
            "label": "Projects",
            "text": "Soudobe metody zpracovani, analyzy a zobrazovani multimedialnich a 3D dat , BUT, Vnitrni projekty VUT, FIT-S-23-8278, start: 2023-03-01, end: 2026-02-28, completed"
        },
        "research_groups": {
            "label": "Research groups",
            "text": "Speech Data Mining Research Group BUT Speech@FIT (RG SPEECH)"
        },
        "departments": {
            "label": "Departments",
            "text": "Department of Computer Graphics and Multimedia (DCGM)"
        }
    }
}